{"nodes": [{"id": "randstad_bot_session", "label": "Randstad Bot Session", "file_type": "document", "source_file": "Randstad/applied_jobs.txt", "source_location": null, "source_url": null, "captured_at": "2026-04-21", "author": null, "contributor": null}, {"id": "randstad_applied_jobs", "label": "Randstad Applied Jobs Log", "file_type": "document", "source_file": "Randstad/applied_jobs.txt", "source_location": null, "source_url": null, "captured_at": "2026-04-21", "author": null, "contributor": null}, {"id": "randstad_session_stats_2026_04_21", "label": "Randstad Session Stats 2026-04-21", "file_type": "document", "source_file": "Randstad/applied_jobs.txt", "source_location": "line 1-103", "source_url": null, "captured_at": "2026-04-21", "author": null, "contributor": null}, {"id": "randstad_zero_applied", "label": "Randstad Zero Applications (All Skipped/Uncertain)", "file_type": "document", "source_file": "Randstad/applied_jobs.txt", "source_location": null, "source_url": null, "captured_at": "2026-04-21", "author": null, "contributor": null}], "edges": [{"source": "randstad_bot_session", "target": "randstad_applied_jobs", "relation": "references", "confidence": "EXTRACTED", "confidence_score": 1.0, "source_file": "Randstad/applied_jobs.txt", "source_location": null, "weight": 1.0}, {"source": "randstad_applied_jobs", "target": "randstad_session_stats_2026_04_21", "relation": "references", "confidence": "EXTRACTED", "confidence_score": 1.0, "source_file": "Randstad/applied_jobs.txt", "source_location": "line 1-46", "weight": 1.0}, {"source": "randstad_session_stats_2026_04_21", "target": "randstad_zero_applied", "relation": "references", "confidence": "EXTRACTED", "confidence_score": 1.0, "source_file": "Randstad/applied_jobs.txt", "source_location": "line 46", "weight": 1.0}, {"source": "randstad_applied_jobs", "target": "job_deduplication", "relation": "implements", "confidence": "INFERRED", "confidence_score": 0.85, "source_file": "Randstad/applied_jobs.txt", "source_location": null, "weight": 1.0}, {"source": "randstad_bot_session", "target": "roberthalf_bot_session", "relation": "semantically_similar_to", "confidence": "INFERRED", "confidence_score": 0.88, "source_file": "Randstad/applied_jobs.txt", "source_location": null, "weight": 0.88}], "hyperedges": [{"id": "randstad_bot_output_triad", "label": "Randstad Bot Output Files: Applied + Scanned + Failed Logs", "nodes": ["randstad_applied_jobs", "randstad_scanned_jobs", "randstad_failed_jobs"], "relation": "implement", "confidence": "EXTRACTED", "confidence_score": 0.95, "source_file": "Randstad/applied_jobs.txt"}]}